gv100ad/__init__.py
gv100ad/reader.py
gv100ad/entities/__init__.py
gv100ad/entities/base_record.py
gv100ad/entities/district.py
gv100ad/entities/district_type.py
gv100ad/entities/federale_state.py
gv100ad/entities/government_region.py
gv100ad/entities/municipal_association.py
gv100ad/entities/municipal_association_type.py
gv100ad/entities/municipality.py
gv100ad/entities/municipality_type.py
gv100ad/entities/region.py
gv100ad_py-0.1.4.dist-info/LICENSE
gv100ad_py-0.1.4.dist-info/METADATA
gv100ad_py-0.1.4.dist-info/WHEEL
gv100ad_py-0.1.4.dist-info/top_level.txt
gv100ad_py-0.1.4.dist-info/RECORD
