Metadata-Version: 2.1
Name: gv100ad-py
Version: 0.1.4
Summary: A reader for the official GV100AD (Gemeindeverzeichnis) file from Destatis
Author-email: STÜBER SYSTEMS GmbH <opensource@stueber.de>
Project-URL: Repository, https://github.com/openpotato/gv100ad-py.git
Project-URL: Issues, https://github.com/openpotato/gv100ad-py/issues
Keywords: gv100ad,Gemeindeverzeichnis
Classifier: Development Status :: 4 - Beta
Classifier: Framework :: AsyncIO
Classifier: Intended Audience :: Developers
Classifier: License :: OSI Approved :: MIT License
Classifier: Operating System :: OS Independent
Classifier: Programming Language :: Python :: 3 :: Only
Classifier: Programming Language :: Python :: 3.8
Classifier: Programming Language :: Python :: 3.9
Classifier: Programming Language :: Python :: 3.10
Classifier: Programming Language :: Python :: 3.11
Classifier: Programming Language :: Python :: 3.12
Classifier: Programming Language :: Python :: 3.13
Classifier: Topic :: Software Development
Classifier: Topic :: Software Development :: Libraries
Classifier: Topic :: Software Development :: Libraries :: Python Modules
Requires-Python: >=3.8
License-File: LICENSE
